orchestra_server/__init__.py
orchestra_server/config.py
orchestra_server/server.py
mseep_eunomia_mcp_server-0.0.6.dist-info/METADATA
mseep_eunomia_mcp_server-0.0.6.dist-info/WHEEL
mseep_eunomia_mcp_server-0.0.6.dist-info/entry_points.txt
mseep_eunomia_mcp_server-0.0.6.dist-info/licenses/LICENSE
mseep_eunomia_mcp_server-0.0.6.dist-info/RECORD
