Metadata-Version: 2.4
Name: mseep-eunomia-mcp-server
Version: 0.0.6
Project-URL: Repository, https://github.com/whataboutyou-ai/eunomia-MCP-server
Author-email: mseep <support@skydeck.ai>
License: Apache-2.0 license
License-File: LICENSE
Requires-Python: >=3.12
Requires-Dist: eunomia-ai
Requires-Dist: mcp>=1.1.2
Requires-Dist: pip
Requires-Dist: pydantic-settings>=2.1.0
Requires-Dist: pydantic>=2.8.0
Requires-Dist: python-dotenv==1.0.0
Requires-Dist: uv
